dmpcrl/__init__.py
dmpcrl/agents/__init__.py
dmpcrl/agents/lstd_ql_coordinator.py
dmpcrl/core/__init__.py
dmpcrl/core/admm.py
dmpcrl/core/consensus.py
dmpcrl/mpc/__init__.py
dmpcrl/mpc/mpc_admm.py
dmpcrl/utils/__init__.py
dmpcrl/utils/discretisation.py
dmpcrl/utils/tikz.py
dmpcrl-1.0.2.dist-info/LICENSE
dmpcrl-1.0.2.dist-info/METADATA
dmpcrl-1.0.2.dist-info/WHEEL
dmpcrl-1.0.2.dist-info/top_level.txt
dmpcrl-1.0.2.dist-info/RECORD
