Metadata-Version: 2.1
Name: dmpcrl
Version: 1.0.2
Summary: Distributed Reinforcement Learning with  Distributed Model Predictive Control
Author-email: Samuel Mallick <sam.mallick.97@gmail.com>
License: MIT
Project-URL: Homepage, https://github.com/SamuelMallick/distributed-mpc-reinforcement-learning
Classifier: Programming Language :: Python :: 3.8
Classifier: Programming Language :: Python :: 3.9
Classifier: Programming Language :: Python :: 3.10
Classifier: Programming Language :: Python :: 3.11
Classifier: License :: OSI Approved :: MIT License
Classifier: Operating System :: OS Independent
Classifier: Topic :: Scientific/Engineering :: Mathematics
Requires-Python: >=3.8
License-File: LICENSE
Requires-Dist: csnlp >=1.5.7
Requires-Dist: mpcrl >=1.1.7
Requires-Dist: numpy >=1.24.4
Requires-Dist: casadi >=3.6.3
Requires-Dist: scipy >=1.11.0
Requires-Dist: gymnasium >=0.28.1
Requires-Dist: matplotlib >=3.7.1
